{
    "name": "US-Electricity-ETL",
    "image": "docker.io/rkrispin/us_electricity_etl:dev.0.0.0.9000",
    "customizations": {
        "vscode": {
            
            "extensions": [
                "quarto.quarto",
                "ms-azuretools.vscode-docker",
                "ms-python.python",
                "rdebugger.r-debugger",
                "ms-vscode-remote.remote-containers",
                "yzhang.markdown-all-in-one",
                "reditorsupport.r",
                "redhat.vscode-yaml",
                "REditorSupport.r",
                "REditorSupport.r-lsp", 
                "RDebugger.r-debugger" 
            ]
        }
    },
    "remoteEnv": {
        "EIA_API_KEY": "${localEnv:EIA_API_KEY}"
    },
    "postCreateCommand": "radian"
}